DocsService/__init__.py
DocsService/__main__.py
DocsService/api.py
DocsService/api_test.py
DocsService/const.py
DocsService/service.py
DocsService/tools.py
pih_doc-1.0.dist-info/METADATA
pih_doc-1.0.dist-info/WHEEL
pih_doc-1.0.dist-info/entry_points.txt
pih_doc-1.0.dist-info/top_level.txt
pih_doc-1.0.dist-info/RECORD
