Metadata-Version: 2.1
Name: pih-doc
Version: 1.0
Summary: PIH Documents service module
Home-page: https://pacifichosp.com/
Author: Nikita Karachentsev
Author-email: it@pacifichosp.com
License: MIT
Requires-Dist: ipih
